{
  "slug_fr": "objectif-professionnel-exemples",
  "slug_en": "professional-objective-examples",
  "slug_ar": "hadaf-mihani-amthila",
  "title_fr": "Objectif professionnel : exemples concrets et efficaces",
  "title_en": "Professional Objective: Concrete and Effective Examples",
  "title_ar": "الهدف المهني: أمثلة ملموسة وفعالة",
  "description_fr": "Guide complet sur objectif professionnel : exemples concrets et efficaces. Conseils pratiques et exemples pour créer un CV professionnel.",
  "description_en": "Complete guide on professional objective: concrete and effective examples. Practical tips and examples to create a professional CV.",
  "description_ar": "دليل شامل حول الهدف المهني: أمثلة ملموسة وفعالة. نصائح عملية وأمثلة لإنشاء سيرة ذاتية مهنية.",
  "category": "cv",
  "keywords_fr": [
    "objectif professionnel",
    "exemples CV",
    "rédaction CV",
    "accroche CV",
    "objectif CV"
  ],
  "keywords_en": [
    "professional objective",
    "CV examples",
    "CV writing",
    "CV hook",
    "CV objective"
  ],
  "keywords_ar": [
    "الهدف المهني",
    "أمثلة السيرة الذاتية",
    "كتابة السيرة الذاتية",
    "جذب السيرة الذاتية",
    "هدف السيرة الذاتية"
  ],
  "date": "2025-12-25",
  "image": "/assets/blog/default-cv.svg"
}