{
  "slug_fr": "cv-sans-experience",
  "slug_en": "cv-without-experience",
  "slug_ar": "cv-bila-khibra",
  "title_fr": "Comment faire un CV quand on n'a pas d'expérience",
  "title_en": "How to Make a CV When You Have No Experience",
  "title_ar": "كيفية إنشاء سيرة ذاتية بدون خبرة",
  "description_fr": "Guide complet sur comment faire un cv quand on n'a pas d'expérience. Conseils pratiques et exemples pour créer un CV professionnel.",
  "description_en": "Complete guide on how to make a cv when you have no experience. Practical tips and examples to create a professional CV.",
  "description_ar": "دليل شامل حول كيفية إنشاء سيرة ذاتية بدون خبرة. نصائح عملية وأمثلة لإنشاء سيرة ذاتية مهنية.",
  "category": "cv",
  "keywords_fr": [
    "CV étudiant",
    "premier CV",
    "CV sans expérience",
    "conseils CV",
    "CV débutant"
  ],
  "keywords_en": [
    "student CV",
    "first CV",
    "CV without experience",
    "CV tips",
    "beginner CV"
  ],
  "keywords_ar": [
    "سيرة ذاتية طالب",
    "أول سيرة ذاتية",
    "سيرة ذاتية بدون خبرة",
    "نصائح السيرة الذاتية",
    "سيرة ذاتية مبتدئ"
  ],
  "date": "2025-12-25",
  "image": "/assets/blog/default-cv.svg"
}