{
  "title_fr": "Comment devenir développeur web en 2025 : Guide complet formation, salaire et compétences",
  "slug_fr": "comment-devenir-developpeur-web-2025",
  "description_fr": "Guide complet sur comment devenir développeur web en 2025 : guide complet formation, salaire et compétences",
  "title_en": "How to Become a Web Developer in 2025: Complete Guide to Training, Salary and Skills",
  "slug_en": "how-to-become-web-developer-2025",
  "description_en": "Complete guide about how to become a web developer in 2025: complete guide to training, salary and skills",
  "title_ar": "كيف تصبح مطور ويب في 2025: دليل شامل للتدريب والراتب والمهارات",
  "slug_ar": "كيف-تصبح-مطور-ويب-2025",
  "description_ar": "دليل شامل حول كيف تصبح مطور ويب في 2025: دليل شامل للتدريب والراتب والمهارات",
  "category": "métiers",
  "datePublication": "2025-01-15"
}